ochanticipy/__init__.py
ochanticipy/_version.py
ochanticipy/config/__init__.py
ochanticipy/config/countryconfig.py
ochanticipy/config/pathconfig.py
ochanticipy/config/countries/afg.yaml
ochanticipy/config/countries/bdi.yaml
ochanticipy/config/countries/bfa.yaml
ochanticipy/config/countries/bgd.yaml
ochanticipy/config/countries/caf.yaml
ochanticipy/config/countries/cmr.yaml
ochanticipy/config/countries/cod.yaml
ochanticipy/config/countries/col.yaml
ochanticipy/config/countries/eth.yaml
ochanticipy/config/countries/hti.yaml
ochanticipy/config/countries/irq.yaml
ochanticipy/config/countries/lby.yaml
ochanticipy/config/countries/mli.yaml
ochanticipy/config/countries/mmr.yaml
ochanticipy/config/countries/moz.yaml
ochanticipy/config/countries/mwi.yaml
ochanticipy/config/countries/ner.yaml
ochanticipy/config/countries/nga.yaml
ochanticipy/config/countries/npl.yaml
ochanticipy/config/countries/pse.yaml
ochanticipy/config/countries/sdn.yaml
ochanticipy/config/countries/som.yaml
ochanticipy/config/countries/ssd.yaml
ochanticipy/config/countries/syr.yaml
ochanticipy/config/countries/tcd.yaml
ochanticipy/config/countries/ukr.yaml
ochanticipy/config/countries/ven.yaml
ochanticipy/config/countries/yem.yaml
ochanticipy/datasources/__init__.py
ochanticipy/datasources/datasource.py
ochanticipy/datasources/chirps/__init__.py
ochanticipy/datasources/chirps/chirps.py
ochanticipy/datasources/codab/__init__.py
ochanticipy/datasources/codab/codab.py
ochanticipy/datasources/fewsnet/__init__.py
ochanticipy/datasources/fewsnet/fewsnet.py
ochanticipy/datasources/glofas/__init__.py
ochanticipy/datasources/glofas/forecast.py
ochanticipy/datasources/glofas/glofas.py
ochanticipy/datasources/glofas/reanalysis.py
ochanticipy/datasources/iri/__init__.py
ochanticipy/datasources/iri/iri_seasonal_forecast.py
ochanticipy/datasources/usgs/__init__.py
ochanticipy/datasources/usgs/ndvi_base.py
ochanticipy/datasources/usgs/ndvi_products.py
ochanticipy/utils/__init__.py
ocha_anticipy-1.1.3.dist-info/LICENSE
ocha_anticipy-1.1.3.dist-info/METADATA
ocha_anticipy-1.1.3.dist-info/WHEEL
ocha_anticipy-1.1.3.dist-info/top_level.txt
ocha_anticipy-1.1.3.dist-info/RECORD
