Metadata-Version: 2.1
Name: ocha-anticipy
Version: 1.1.3
Summary: Access data for anticipating humanitarian risk
Home-page: https://github.com/OCHA-DAP/ocha-anticipy
Author: Data Science Team, UN OCHA Centre for Humanitarian Data
Author-email: centrehumdata@un.org
License: GPLv3
Project-URL: Documentation, https://ocha-anticipy.readthedocs.io/en/latest/
Project-URL: Changes, https://github.com/OCHA-DAP/ocha-anticipy/blob/main/CHANGELOG.rst
Project-URL: PyPI Releases, https://pypi.org/project/ocha-anticipy/
Project-URL: Source Code, https://github.com/OCHA-DAP/ocha-anticipy/
Project-URL: Issue Tracker, https://github.com/OCHA-DAP/ocha-anticipy/issues/
Classifier: Development Status :: 5 - Production/Stable
Classifier: Intended Audience :: Developers
Classifier: Intended Audience :: Science/Research
Classifier: License :: OSI Approved :: GNU General Public License v3 (GPLv3)
Classifier: Natural Language :: English
Classifier: Operating System :: OS Independent
Classifier: Programming Language :: Python :: 3 :: Only
Requires-Python: >=3.8
License-File: LICENSE
Requires-Dist: cftime
Requires-Dist: geopandas
Requires-Dist: hdx-python-api >=5.6.4
Requires-Dist: hdx-python-country
Requires-Dist: netCDF4
Requires-Dist: numpy
Requires-Dist: pydantic <2.0
Requires-Dist: python-dateutil
Requires-Dist: pyyaml
Requires-Dist: rasterio
Requires-Dist: requests
Requires-Dist: rioxarray
Requires-Dist: wrapt
Requires-Dist: xarray[parallel]
Provides-Extra: dev
Requires-Dist: cdsapi ; extra == 'dev'
Requires-Dist: cfgrib ; extra == 'dev'
Requires-Dist: pytest ; extra == 'dev'
Requires-Dist: pytest-cov ; extra == 'dev'
Requires-Dist: pytest-mock ; extra == 'dev'
Requires-Dist: tox ; extra == 'dev'
Requires-Dist: extras-require ; extra == 'dev'
Requires-Dist: sphinx ; extra == 'dev'
Requires-Dist: sphinx-rtd-theme ; extra == 'dev'
Requires-Dist: sphinxcontrib-apidoc ; extra == 'dev'
Requires-Dist: pre-commit ; extra == 'dev'
Provides-Extra: doc
Requires-Dist: extras-require ; extra == 'doc'
Requires-Dist: sphinx ; extra == 'doc'
Requires-Dist: sphinx-rtd-theme ; extra == 'doc'
Requires-Dist: sphinxcontrib-apidoc ; extra == 'doc'
Provides-Extra: full
Requires-Dist: cdsapi ; extra == 'full'
Requires-Dist: cfgrib ; extra == 'full'
Provides-Extra: glofas
Requires-Dist: cdsapi ; extra == 'glofas'
Requires-Dist: cfgrib ; extra == 'glofas'
Provides-Extra: test
Requires-Dist: cdsapi ; extra == 'test'
Requires-Dist: cfgrib ; extra == 'test'
Requires-Dist: pytest ; extra == 'test'
Requires-Dist: pytest-cov ; extra == 'test'
Requires-Dist: pytest-mock ; extra == 'test'
Requires-Dist: tox ; extra == 'test'
